README.md
setup.cfg
setup.py
outliers_ashwin/__init__.py
outliers_ashwin/outliers_ashwin.py
outliers_ashwin.egg-info/PKG-INFO
outliers_ashwin.egg-info/SOURCES.txt
outliers_ashwin.egg-info/dependency_links.txt
outliers_ashwin.egg-info/top_level.txt