Metadata-Version: 2.1
Name: outliers-ashwin
Version: 0.0.3
Summary: An outlier removal method (By removing rows)
Home-page: https://github.com/ash-1999/outliers_ashwin
Author: ashwin_menon
Author-email: ashwin.s.menon1999@gmail.com
License: UNKNOWN
Download-URL: https://github.com/ash_1999/outliers_ashwin/archive/0.0.3.tar.gz
Platform: UNKNOWN
Classifier: Programming Language :: Python :: 3
Classifier: License :: OSI Approved :: MIT License
Classifier: Operating System :: OS Independent
Requires-Python: >=3.6
